setup.cfg
setup.py
scripts/dax
scripts/tinyber_gen
tests/__init__.py
tests/gen_choice_ber.py
tests/test_choice.py
tests/test_int_match.py
tests/utils.py
tinyber/__init__.py
tinyber/_codec.c
tinyber/ber.py
tinyber/c_nodes.py
tinyber/codec.py
tinyber/gen.py
tinyber/nodes.py
tinyber/py_nodes.py
tinyber/walker.py
tinyber/writer.py
tinyber.egg-info/PKG-INFO
tinyber.egg-info/SOURCES.txt
tinyber.egg-info/dependency_links.txt
tinyber.egg-info/requires.txt
tinyber.egg-info/top_level.txt