Metadata-Version: 1.0
Name: tinyber
Version: 0.0.1
Summary: ASN.1 code generator for Python and C
Home-page: https://github.com/cloudtools/tinyber
Author: UNKNOWN
Author-email: UNKNOWN
License: UNKNOWN
Platform: UNKNOWN
